setup.py
myadipkg/__init__.py
myadipkg/calculator.py
myadipkg_ws.egg-info/PKG-INFO
myadipkg_ws.egg-info/SOURCES.txt
myadipkg_ws.egg-info/dependency_links.txt
myadipkg_ws.egg-info/top_level.txt