Metadata-Version: 2.1
Name: myadipkg-ws
Version: 0.0.1
Summary: ADI python Package module
Home-page: https://github.com/waseema
Author: waseema
Author-email: vaseemamit@gmail.com
License: UNKNOWN
Platform: UNKNOWN
Classifier: Programming Language :: Python :: 3
Classifier: Operating System :: OS Independent
